odoo/addons/contract_invoice_start_end_dates/README.rst
odoo/addons/contract_invoice_start_end_dates/__init__.py
odoo/addons/contract_invoice_start_end_dates/__manifest__.py
odoo/addons/contract_invoice_start_end_dates/i18n/contract_invoice_start_end_dates.pot
odoo/addons/contract_invoice_start_end_dates/i18n/da.po
odoo/addons/contract_invoice_start_end_dates/i18n/es.po
odoo/addons/contract_invoice_start_end_dates/i18n/fr.po
odoo/addons/contract_invoice_start_end_dates/i18n/hr.po
odoo/addons/contract_invoice_start_end_dates/i18n/it.po
odoo/addons/contract_invoice_start_end_dates/i18n/nl.po
odoo/addons/contract_invoice_start_end_dates/i18n/pt_BR.po
odoo/addons/contract_invoice_start_end_dates/models/__init__.py
odoo/addons/contract_invoice_start_end_dates/models/contract_line.py
odoo/addons/contract_invoice_start_end_dates/readme/CONTRIBUTORS.md
odoo/addons/contract_invoice_start_end_dates/readme/DESCRIPTION.md
odoo/addons/contract_invoice_start_end_dates/static/description/icon.png
odoo/addons/contract_invoice_start_end_dates/static/description/index.html
odoo/addons/contract_invoice_start_end_dates/tests/__init__.py
odoo/addons/contract_invoice_start_end_dates/tests/test_contract_invoice_start_end_dates.py
odoo_addon_contract_invoice_start_end_dates-18.0.1.0.0.4.dist-info/METADATA
odoo_addon_contract_invoice_start_end_dates-18.0.1.0.0.4.dist-info/WHEEL
odoo_addon_contract_invoice_start_end_dates-18.0.1.0.0.4.dist-info/top_level.txt
odoo_addon_contract_invoice_start_end_dates-18.0.1.0.0.4.dist-info/RECORD
